{
  "北京奔驰": "北京メルセデス・ベンツ",
  "紧凑型SUV": "コンパクトSUV",
  "汽油": "ガソリン",
  "汽油+48V轻混系统": "ガソリン＋48Vマイルドハイブリッドシステム",
  "国VI": "国6排ガス規制",
  "7挡湿式双离合": "7速湿式デュアルクラッチ",
  "8挡湿式双离合": "8速湿式デュアルクラッチ",
  "5门5座SUV": "5ドア5人乗りSUV",
  "5门7座SUV": "5ドア7人乗りSUV",
  "1.3T 163马力 L4": "1.3T 163馬力 L4",
  "2.0T 190马力 L4": "2.0T 190馬力 L4",
  "4638*1834*1696": "4638×1834×1696mm",
  "4638*1834*1701": "4638×1834×1701mm",
  "4638*1834*1706": "4638×1834×1706mm",
  "● 三年不限公里": "● 3年走行距離無制限保証",
  "SUV": "SUV",
  "平开门": "開き戸",
  "● 5": "● 5人乗り",
  "● 7": "● 7人乗り",
  "涡轮增压": "ターボチャージャー",
  "横置": "横置エンジン",
  "DOHC": "DOHC",
  "95号": "95オクタン",
  "直喷": "直噴",
  "铝合金": "アルミ合金",
  "湿式双离合变速箱(DCT)": "湿式デュアルクラッチトランスミッション(DCT)",
  "● 前置前驱": "● 前置前輪駆動",
  "● 前置四驱": "● 前置四輪駆動",
  "● 适时四驱": "● 走行状況に応じた四輪駆動",
  "● 多片离合器": "● 多板クラッチ",
  "● 麦弗逊式独立悬架": "● マクファーソン独立サスペンション",
  "● 多连杆式独立悬架": "● マルチリンク独立サスペンション",
  "● 电动助力": "● 電動パワーステアリング",
  "承载式": "モノコックボディ",
  "● 通风盘式": "● ベンチレーテッドディスク",
  "● 盘式": "● ディスクブレーキ",
  "● 电子驻车": "● 電子パーキングブレーキ",
  "● 235/55 R18": "● 235/55 R18タイヤ",
  "● 235/50 R19": "● 235/50 R19タイヤ",
  "● 无": "● なし",
  "主 ● / 副 ●": "運転席 ● / 助手席 ●",
  "前 ● / 后": "前輪 ● / 後輪",
  "前 ● / 后 ○ (3400元)": "前輪 ● / 後輪 ○（3400元）",
  "前 ● / 后 ●": "前輪 ● / 後輪 ●",
  "● 胎压显示": "● タイヤ空気圧表示",
  "● 前排\n● 第二排": "● 前席\n● 2列目席",
  "● 运动\n● 经济\n● 标准/舒适": "● スポーツ\n● エコ\n● 標準／コンフォート",
  "● 倒车影像": "● リアビューカメラ",
  "● 倒车影像\n○ 360度全景影像 (6000元)": "● リアビューカメラ\n○ 360度全方位カメラ（6000元）",
  "● 2个": "● 2個",
  "● 2个\n○ 5个": "● 2個\n○ 5個",
  "● 12个": "● 12個",
  "● 全速自适应巡航": "● 全速度域対応アダプティブクルーズコントロール",
  "● L2": "● レベル2",
  "● 高德": "● 高徳（ガオデ）ナビ",
  "● 铝合金": "● アルミ合金",
  "● 遥控钥匙": "● リモコンキー",
  "○ 全车 (3900元)": "○ 全車（3900元）",
  "● 全车": "● 全車",
  "● LED": "● LED",
  "○ 几何多光束 (5400元)": "○ ジオメトリックマルチビーム (5400元)",
  "● 分段式电动天窗": "● 分割式電動サンルーフ",
  "● 主驾驶+照明灯\n● 副驾驶+照明灯": "● 運転席＋照明灯\n● 助手席＋照明灯",
  "● 雨量感应式": "● 雨量感応式",
  "● 电动调节\n● 电动折叠\n● 后视镜加热\n● 锁车自动折叠": "● 電動調整\n● 電動格納\n● ドアミラー加熱\n● 施錠時自動格納",
  "● 电动调节\n● 电动折叠\n● 后视镜加热\n● 倒车自动下翻\n● 锁车自动折叠": "● 電動調整\n● 電動格納\n● ドアミラー加熱\n● バック時自動下向き\n● 施錠時自動格納",
  "● 触控液晶屏": "● タッチ液晶画面",
  "● 10.25英寸": "● 10.25インチ",
  "● 支持CarPlay\n● 支持Android Auto": "● CarPlay対応\n● Android Auto対応",
  "● 多媒体系统\n● 导航\n● 电话\n● 空调": "● マルチメディアシステム\n● ナビゲーション\n● 電話\n● エアコン",
  "● 你好，奔驰": "● こんにちは、メルセデス",
  "● MBUX": "● MBUX",
  "● 4G": "● 4G",
  "● 车况查询/诊断\n● 车辆定位/寻车\n● 预约保养/维修": "● 車両状態確認/診断\n● 車両位置特定/車探し\n● 点検/整備予約",
  "● 车门控制\n● 车辆启动\n● 车况查询/诊断\n● 车辆定位/寻车\n● 预约保养/维修": "● ドア操作\n● エンジン始動\n● 車両状態確認/診断\n● 車両位置特定/車探し\n● 点検/整備予約",
  "● 真皮": "● 本革",
  "● 手动上下+前后调节": "● 手動上下＋前後調整",
  "● 电子式怀挡换挡": "● 電子式コラムシフト",
  "● 彩色": "● カラー",
  "○ (9000元)": "○ (9000元)",
  "● 手动防眩目": "● 手動防眩",
  "○ (3000元)": "○ (3000元)",
  "● USB\n● Type-C": "● USB\n● Type-C",
  "● 前排3个/后排2个": "● 前席3個／後席2個",
  "● 前排3个/后排4个": "● 前席3個／後席4個",
  "● 前排": "● 前席",
  "● 仿皮": "● 合成皮革",
  "● 前后调节\n● 靠背调节\n● 高低调节(4向)\n● 腿托调节\n● 腰部支撑(4向)": "● 前後調整\n● 背もたれ調整\n● 高さ調整（4方向）\n● レッグレスト調整\n● 腰部サポート（4方向）",
  "● 前后调节\n● 靠背调节\n● 高低调节(4向)": "● 前後調整\n● 背もたれ調整\n● 高さ調整（4方向）",
  "● 前后调节\n● 靠背调节\n● 高低调节(4向)\n○ 腿托调节": "● 前後調整\n● 背もたれ調整\n● 高さ調整（4方向）\n○ レッグレスト調整",
  "● 前后调节\n● 靠背调节\n● 高低调节(4向)\n● 腿托调节": "● 前後調整\n● 背もたれ調整\n● 高さ調整（4方向）\n● レッグレスト調整",
  "主 ● / 副": "運転席 ● / 助手席",
  "主 ● / 副 ○ (2900元)": "運転席 ● / 助手席 ○ (2900元)",
  "○ 加热 (2600元)": "○ ヒーター付 (2600元)",
  "● 加热": "● ヒーター付",
  "● 靠背调节": "● 背もたれ調整",
  "● 前后调节\n● 靠背调节": "● 前後調整\n● 背もたれ調整",
  "● 2-3-2": "● 2-3-2",
  "● 比例放倒": "● 分割可倒式",
  "○ Burmester柏林之声 (8200元)": "○ Burmesterベルリン音響 (8200元)",
  "● 7喇叭": "● 7スピーカー",
  "● 7喇叭\n○ 12喇叭": "● 7スピーカー\n○ 12スピーカー",
  "○ 64色 (2400元)": "○ 64色 (2400元)",
  "● 64色": "● 64色",
  "● 自动空调": "● オートエアコン",
  "○ (1500元)": "○ (1500元)",
  "○ 选配 (4600元)": "○ オプション (4600元)"
}