{
  "2026年モデル 东方曜 1.5TD 惊鸿版": "2026年モデル 東方曜 1.5TD 驚鴻版",
  "2026年モデル 东方曜 1.5TD 扶摇版": "2026年モデル 東方曜 1.5TD 扶搖版",
  "2026年モデル 东方曜 1.5TD 昆仑版": "2026年モデル 東方曜 1.5TD 崑崙版",
  "2026年モデル 东方曜 2.0TD 霄汉版": "2026年モデル 東方曜 2.0TD 霄漢版",
  "2026年モデル 东方曜 2.0TD 揽星版": "2026年モデル 東方曜 2.0TD 攬星版",
  "2026年モデル 东方曜 2.0TD 望月版": "2026年モデル 東方曜 2.0TD 望月版",
  "2025年モデル 东方曜 2.0TD 今朝版": "2025年モデル 東方曜 2.0TD 今朝版",
  "2025年モデル 东方曜 2.0TD 揽星版": "2025年モデル 東方曜 2.0TD 攬星版",
  "2025年モデル 东方曜 2.0TD 望月版": "2025年モデル 東方曜 2.0TD 望月版",
  "2025年モデル 东方曜 1.5TD 惊鸿版+": "2025年モデル 東方曜 1.5TD 驚鴻版+",
  "2025年モデル 东方曜 1.5TD 扶摇版": "2025年モデル 東方曜 1.5TD 扶搖版",
  "2025年モデル 东方曜 1.5TD 昆仑版": "2025年モデル 東方曜 1.5TD 崑崙版",
  "2025年モデル 东方曜 1.5TD 惊鸿版": "2025年モデル 東方曜 1.5TD 驚鴻版",
  "2024年モデル 油混 1.5TD 星云版": "2024年モデル ハイブリッド 1.5TD 星雲版",
  "2024年モデル 油混 1.5TD 星河版": "2024年モデル ハイブリッド 1.5TD 星河版",
  "2024年モデル 油混 1.5TD 天宫版": "2024年モデル ハイブリッド 1.5TD 天宮版"
}