{
  "一汽奥迪": "一汽アウディ",
  "紧凑型SUV": "コンパクトSUV",
  "汽油": "ガソリン",
  "国VI": "国6排ガス規制",
  "7挡湿式双离合": "7速湿式デュアルクラッチ",
  "5门5座SUV": "5ドア5人乗りSUV",
  "1.5T 160马力 L4": "1.5T 160馬力 L4",
  "2.0T 186马力 L4": "2.0T 186馬力 L4",
  "2.0T 220马力 L4": "2.0T 220馬力 L4",
  "4498*1848*1614": "4498×1848×1614（mm）",
  "● 三年或10万公里": "● 3年または10万km保証",
  "SUV": "SUV",
  "平开门": "開きドア",
  "● 5": "● 5（ドア数）",
  "DSV": "DSV",
  "DTH": "DTH",
  "DTJ": "DTJ",
  "涡轮增压": "ターボチャージャー",
  "横置": "横置エンジン",
  "DOHC": "DOHC（ダブルカムシャフト）",
  "95号": "95オクタンガソリン",
  "直喷": "直噴",
  "铝合金": "アルミ合金",
  "铸铁": "鋳鉄",
  "湿式双离合变速箱(DCT)": "湿式デュアルクラッチトランスミッション（DCT）",
  "● 前置前驱": "● フロントエンジン・前輪駆動",
  "● 前置四驱": "● フロントエンジン・四輪駆動",
  "● 适时四驱": "● 走行状況に応じた四輪駆動（オンデマンド4WD）",
  "● 多片离合器": "● 多板クラッチ",
  "● 麦弗逊式独立悬架": "● マクファーソン独立サスペンション",
  "● 多连杆式独立悬架": "● マルチリンク独立サスペンション",
  "● 电动助力": "● 電動パワーステアリング",
  "承载式": "モノコックボディ",
  "● 通风盘式": "● ベンチレーテッドディスク",
  "● 盘式": "● ディスクブレーキ",
  "● 电子驻车": "● 電子パーキングブレーキ",
  "● 235/55 R18\n○ 235/50 R19 (2500元)": "● 235/55 R18\n○ 235/50 R19（2500元）",
  "● 235/50 R19": "● 235/50 R19",
  "● 非全尺寸": "● フルサイズではない（スペアタイヤ）",
  "主 ● / 副 ●": "運転席 ● / 助手席 ●",
  "前 ● / 后 ○ (1700元)": "前席 ● / 後席 ○（1700元）",
  "前 ● / 后 ●": "前席 ● / 後席 ●",
  "● 胎压报警": "● タイヤ空気圧警報",
  "● 全车": "● 全車輪対応",
  "● 运动\n○ 经济\n○ 标准/舒适\n○ 自定义/个性化": "● スポーツ\n○ エコ\n○ 標準／快適\n○ カスタム／パーソナライズ",
  "● 运动\n○ 经济\n○ 标准/舒适\n● 自定义/个性化": "● スポーツ\n○ エコ\n○ 標準／快適\n● カスタム／パーソナライズ",
  "● 运动\n● 经济\n● 标准/舒适\n● 自定义/个性化": "● スポーツ\n● エコ\n● 標準／快適\n● カスタム／パーソナライズ",
  "○ 倒车影像 (2500元)\n○ 360度全景影像 (7500元)": "○ リアビューカメラ（2500元）\n○ 360度全方位カメラ（7500元）",
  "● 倒车影像\n○ 360度全景影像 (5000元)": "● リアビューカメラ\n○ 360度全方位カメラ（5000元）",
  "● 定速巡航\n○ 全速自适应巡航 (7000元)": "● クルーズコントロール\n○ 全速度域対応アダプティブクルーズ（7000元）",
  "● 全速自适应巡航": "● 全速度域対応アダプティブクルーズコントロール",
  "○ L2": "○ レベル2自動運転支援",
  "○ (6500元)": "○ （6500元）",
  "○ (3500元)": "○ （3500元）",
  "○ (5500元)": "○ （5500元）",
  "○ (1500元)": "○ （1500元）",
  "● 运动风格": "● スポーツスタイル",
  "● 铝合金": "● アルミ合金ホイール",
  "● 遥控钥匙": "● リモコンキー",
  "○ 前排": "○ 前席",
  "● 前排": "● 前席",
  "● LED": "● LED",
  "○ 矩阵式 (6000元)": "○ マトリクス式（6000元）",
  "● 矩阵式": "● マトリクス式",
  "○ (500元)": "○ （500元）",
  "● 可开启全景天窗": "● 開閉式パノラマサンルーフ",
  "○ (1000元)": "○ （1000元）",
  "● 主驾驶+照明灯\n● 副驾驶+照明灯": "● 運転席＋照明灯\n● 助手席＋照明灯",
  "● 雨量感应式": "● 雨量感応式",
  "● 电动调节\n○ 电动折叠 (1000元)\n● 后视镜加热\n○ 锁车自动折叠\n○ 自动防眩目 (1000元)": "● 電動調整\n○ 電動格納（1000元）\n● ドアミラー加熱\n○ 施錠時自動格納\n○ 自動防眩目（1000元）",
  "● 电动调节\n● 电动折叠\n● 后视镜加热\n● 倒车自动下翻\n● 锁车自动折叠\n○ 自动防眩目 (1000元)": "● 電動調整\n● 電動格納\n● ドアミラー加熱\n● バック時自動下向き\n● 施錠時自動格納\n○ 自動防眩目（1000元）",
  "● 触控液晶屏": "● タッチ液晶画面",
  "● 10.1英寸": "● 10.1インチ",
  "● 支持CarPlay": "● CarPlay対応",
  "● 4G": "● 4G",
  "● 真皮": "● 本革",
  "● 手动上下+前后调节": "● 手動上下＋前後調整",
  "● 机械挡把换挡": "● メカニカルシフトレバー",
  "● 彩色": "● カラー",
  "● 10.25英寸": "● 10.25インチ",
  "● 12.3英寸": "● 12.3インチ",
  "● 自动防眩目": "● 自動防眩目",
  "● Type-C": "● Type-C",
  "● 前排2个/后排2个": "● 前席2個／後席2個",
  "○ (2000元)": "○ （2000元）",
  "● 仿皮": "● 合成皮革",
  "● 皮/Alcantara混搭": "● 革／アルカンターラコンビ",
  "● 前后调节\n● 靠背调节\n● 高低调节(4向)\n● 腰部支撑(4向)": "● 前後調整\n● 背もたれ調整\n● 高さ調整（4方向）\n● 腰部サポート（4方向）",
  "● 前后调节\n● 靠背调节\n● 高低调节(4向)\n● 腿托调节\n● 腰部支撑(4向)": "● 前後調整\n● 背もたれ調整\n● 高さ調整（4方向）\n● レッグレスト調整\n● 腰部サポート（4方向）",
  "○ 加热 (2500元)": "○ ヒーター（2500元）",
  "● 前后调节\n● 靠背调节": "● 前後調整\n● 背もたれ調整",
  "● 比例放倒": "● 分割可倒式",
  "○ SONOS (8500元)": "○ SONOS（8500元）",
  "○ 12喇叭": "○ 12スピーカー",
  "● 30色": "● 30色",
  "● 自动空调": "● オートエアコン",
  "○ 选配 (6500元)": "○ オプション（6500元）"
}