{
  "一汽-大众": "一汽フォルクスワーゲン",
  "紧凑型SUV": "コンパクトSUV",
  "汽油": "ガソリン",
  "国VI": "国6排ガス規制",
  "7挡干式双离合": "7速乾式デュアルクラッチ",
  "5门5座SUV": "5ドア5人乗りSUV",
  "1.4T 150马力 L4": "1.4T 150馬力 L4",
  "1.5T 160马力 L4": "1.5T 160馬力 L4",
  "4336*1819*1592": "4336×1819×1592（mm）",
  "4319*1819*1592": "4319×1819×1592（mm）",
  "● 三年或10万公里": "● 3年または10万km保証",
  "SUV": "SUV",
  "平开门": "開きドア",
  "● 5": "● 5",
  "DUT": "DUT",
  "DSV": "DSV",
  "EA211-DUT": "EA211-DUT",
  "EA211-DSV": "EA211-DSV",
  "涡轮增压": "ターボチャージャー",
  "横置": "横置エンジン",
  "DOHC": "DOHC",
  "95号": "95オクタン",
  "直喷": "直噴",
  "铝合金": "アルミ合金",
  "干式双离合变速箱(DCT)": "乾式デュアルクラッチトランスミッション（DCT）",
  "● 前置前驱": "● 前置前輪駆動",
  "● 麦弗逊式独立悬架": "● マクファーソン独立サスペンション",
  "● 多连杆式独立悬架": "● マルチリンク独立サスペンション",
  "● 电动助力": "● 電動パワーステアリング",
  "承载式": "モノコックボディ",
  "● 通风盘式": "● ベンチレーテッドディスク",
  "● 盘式": "● ディスクブレーキ",
  "● 电子驻车": "● 電子パーキングブレーキ",
  "● 215/55 R17\n○ 215/50 R18": "● 215/55 R17\n○ 215/50 R18",
  "● 215/50 R18": "● 215/50 R18",
  "○ 非全尺寸 (200元)": "○ フルサイズでない（200元）",
  "○ 非全尺寸": "○ フルサイズでない",
  "○ 后备厢内": "○ トランク内",
  "主 ● / 副 ●": "運転席 ● / 助手席 ●",
  "前 ● / 后": "前席 ● / 後席なし",
  "前 ● / 后 ●": "前席 ● / 後席 ●",
  "● 胎压报警": "● タイヤ空気圧警報",
  "● 全车": "● 全車",
  "● 运动\n● 经济\n● 标准/舒适\n● 自定义/个性化": "● スポーツ\n● エコ\n● 標準/快適\n● カスタム/パーソナライズ",
  "前- / 后 ●": "前なし / 後 ●",
  "● 倒车影像": "● バックカメラ",
  "● 单目": "● 単眼カメラ",
  "● 1个": "● 1個",
  "● 2个": "● 2個",
  "● 4个": "● 4個",
  "● 8个": "● 8個",
  "● 12个": "● 12個",
  "● 1个\n○ 3个": "● 1個\n○ 3個",
  "● 3个": "● 3個",
  "● 定速巡航\n○ 全速自适应巡航 (3000元)": "● クルーズコントロール\n○ 全速度域対応アダプティブクルーズ（3000元）",
  "● 全速自适应巡航": "● 全速度域対応アダプティブクルーズ",
  "○ IQ. Drive": "○ IQ.ドライブ",
  "● IQ. Drive": "● IQ.ドライブ",
  "○ L2": "○ レベル2",
  "● L2": "● レベル2",
  "● 运动风格": "● スポーティスタイル",
  "● 铝合金": "● アルミ合金",
  "○ (2000元)": "○ (2000元)",
  "○ (1200元)": "○ (1200元)",
  "● 遥控钥匙\n● UWB数字钥匙": "● リモコンキー\n● UWBデジタルキー",
  "● 遥控钥匙\n○ UWB数字钥匙 (1200元)": "● リモコンキー\n○ UWBデジタルキー (1200元)",
  "● 遥控钥匙": "● リモコンキー",
  "● 前排": "● 前席",
  "● LED": "● LED",
  "● 矩阵式": "● マトリクス式",
  "● 可开启全景天窗": "● 開閉式パノラマサンルーフ",
  "● 主驾驶+照明灯\n● 副驾驶+照明灯": "● 運転席＋照明灯\n● 助手席＋照明灯",
  "● 雨量感应式": "● 雨量感知式",
  "● 电动调节\n● 后视镜加热": "● 電動調整\n● ドアミラー加熱",
  "● 电动调节\n● 电动折叠\n● 后视镜加热\n● 倒车自动下翻\n● 锁车自动折叠": "● 電動調整\n● 電動格納\n● ドアミラー加熱\n● バック時自動下向き\n● 施錠時自動格納",
  "● 触控液晶屏": "● タッチ液晶画面",
  "● 8英寸": "● 8インチ",
  "● 9.2英寸": "● 9.2インチ",
  "● 支持CarPlay\n● 原厂互联/映射": "● CarPlay対応\n● 純正連携/ミラーリング",
  "● 支持CarPlay\n● 支持CarLife\n● 原厂互联/映射": "● CarPlay対応\n● CarLife対応\n● 純正連携/ミラーリング",
  "● 多媒体系统\n● 导航\n● 电话": "● マルチメディアシステム\n● ナビゲーション\n● 電話機能",
  "● 你好，大众": "● こんにちは、大衆",
  "● 单区域": "● シングルゾーン",
  "● 4G": "● 4G",
  "● 皮质": "● レザー",
  "● 手动上下+前后调节": "● 手動上下＋前後調整",
  "● 机械挡把换挡": "● メカニカルシフトレバー",
  "● 彩色": "● カラー",
  "○ (1000元)": "○ (1000元)",
  "● 8英寸\n○ 10.3英寸": "● 8インチ\n○ 10.3インチ",
  "● 10.3英寸": "● 10.3インチ",
  "● 手动防眩目": "● 手動防眩目",
  "● 自动防眩目": "● 自動防眩目",
  "○ (500元)": "○ (500元)",
  "● USB\n● Type-C": "● USB\n● Type-C",
  "● 前排2个/后排2个": "● 前席2個／後席2個",
  "● 前排3个/后排2个": "● 前席3個／後席2個",
  "● 仿皮": "● 合成皮革",
  "● 前后调节\n● 靠背调节\n● 高低调节(2向)": "● 前後調整\n● 背もたれ調整\n● 高さ調整（2方向）",
  "● 前后调节\n● 靠背调节\n● 高低调节(4向)\n● 腰部支撑(2向)": "● 前後調整\n● 背もたれ調整\n● 高さ調整（4方向）\n● 腰部サポート（2方向）",
  "主 ● / 副": "運転席 ● / 助手席",
  "○ 加热 (1500元)": "○ ヒーター付き (1500元)",
  "○ 加热 (1000元)": "○ ヒーター付き (1000元)",
  "● 比例放倒": "● 分割可倒式",
  "● 4喇叭": "● 4スピーカー",
  "● 6喇叭": "● 6スピーカー",
  "● 单色": "● 単色",
  "● 30色": "● 30色",
  "● 手动空调": "● マニュアルエアコン",
  "● 自动空调": "● オートエアコン",
  "○ 选配 (2000元)": "○ オプション (2000元)",
  "○ 选配 (3000元)": "○ オプション (3000元)",
  "○ 选配 (5500元)": "○ オプション (5500元)"
}