{
  "2026年モデル 2.5L 双擎2WD舒适版": "2026年モデル 2.5L ハイブリッド2WD 快適版",
  "2026年モデル 2.5L 双擎2WD豪华版": "2026年モデル 2.5L ハイブリッド2WD 豪華版",
  "2026年モデル 2.5L 双擎4WD豪华版": "2026年モデル 2.5L ハイブリッド4WD 豪華版",
  "2026年モデル 2.5L 双擎2WD尊贵版": "2026年モデル 2.5L ハイブリッド2WD 上級版",
  "2026年モデル 2.5L 双擎4WD尊贵版": "2026年モデル 2.5L ハイブリッド4WD 上級版",
  "2026年モデル 2.5L 双擎2WD臻享尊贵版": "2026年モデル 2.5L ハイブリッド2WD プレミアム上級版",
  "2026年モデル 2.5L 双擎2WD豪华福祉版": "2026年モデル 2.5L ハイブリッド2WD 豪華福祉版",
  "2026年モデル 2.5L 双擎4WD臻享版": "2026年モデル 2.5L ハイブリッド4WD プレミアム版",
  "2026年モデル 2.5L 双擎2WD至尊版": "2026年モデル 2.5L ハイブリッド2WD 最上級版",
  "2026年モデル 2.5L 双擎2WD铂金版": "2026年モデル 2.5L ハイブリッド2WD プラチナ版"
}