{
  "东风本田": "東風ホンダ",
  "紧凑型SUV": "コンパクトSUV",
  "油电混合": "ハイブリッド",
  "汽油": "ガソリン",
  "国VI": "国6",
  "E-CVT无级变速": "E-CVT無段変速",
  "CVT无级变速": "CVT無段変速",
  "5门5座SUV": "5ドア5人乗りSUV",
  "5门7座SUV": "5ドア7人乗りSUV",
  "2.0L 150马力 L4": "2.0L 150馬力 L4",
  "1.5T 193马力 L4": "1.5T 193馬力 L4",
  "4703*1866*1680": "4703×1866×1680",
  "4703*1866*1690": "4703×1866×1690",
  "4703*1866*1683": "4703×1866×1683",
  "● 三年或10万公里": "● 3年または10万km",
  "SUV": "SUV",
  "平开门": "開きドア",
  "● 5": "● 5人乗り",
  "● 7": "● 7人乗り",
  "LFB22": "LFB22",
  "L15BZ": "L15BZ",
  "自然吸气": "自然吸気",
  "涡轮增压": "ターボチャージャー",
  "横置": "横置き",
  "DOHC": "DOHC",
  "VTEC TURBO": "VTECターボ",
  "92号": "レギュラーガソリン（92）",
  "直喷": "直噴",
  "铝合金": "アルミ合金",
  "单电机": "単一モーター",
  "前置": "前置き",
  "● 锂离子电池": "● リチウムイオン電池",
  "● 十年或20万公里": "● 10年または20万km",
  "无级变速": "無段変速",
  "电子无级变速箱(E-CVT)": "電子制御無段変速機（E-CVT）",
  "无级变速箱(CVT)": "無段変速機（CVT）",
  "● 前置前驱": "● 前置前輪駆動",
  "● 前置四驱": "● 前置4WD",
  "● 适时四驱": "● 走行状況に応じた4WD",
  "● 多片离合器": "● 多板クラッチ",
  "● 麦弗逊式独立悬架": "● マクファーソン式独立サスペンション",
  "● 多连杆式独立悬架": "● マルチリンク式独立サスペンション",
  "● 电动助力": "● 電動パワーステアリング",
  "承载式": "モノコック構造",
  "● 通风盘式": "● ベンチレーテッドディスク",
  "● 盘式": "● ディスクブレーキ",
  "● 电子驻车": "● 電子パーキングブレーキ",
  "● 235/60 R18": "● 235/60 R18タイヤ",
  "● 235/55 R19": "● 235/55 R19タイヤ",
  "● 235/65 R17": "● 235/65 R17タイヤ",
  "● 无": "● なし",
  "● 非全尺寸": "● フルサイズではない",
  "● 主 / 副": "● 運転席/助手席",
  "● 前 / 后": "● 前/後",
  "● 主驾膝部气囊 副驾膝部气囊": "● 運転席・助手席膝部エアバッグ",
  "● 胎压报警": "● タイヤ空気圧警報",
  "● 全车": "● 車両全体",
  "● 运动 经济 标准/舒适 雪地": "● スポーツ・エコノミー・標準/快適・スノー",
  "● 经济 标准/舒适 雪地": "● エコノミー・標準/快適・スノー",
  "● 前- / 后": "● 前-/後",
  "● 倒车影像": "● バックカメラ",
  "● 360度全景影像": "● 360度全方位カメラ",
  "● 360度全景影像 车侧盲区影像": "● 360度全方位カメラ＋サイドブラインドスポットカメラ",
  "● 单目": "● 単眼",
  "● 1个": "● 1個",
  "● 2个": "● 2個",
  "● 5个": "● 5個",
  "● 4个": "● 4個",
  "● 8个": "● 8個",
  "● 定速巡航": "● クルーズコントロール",
  "● 全速自适应巡航": "● 全速度域対応アダプティブクルーズコントロール",
  "● Honda SENSING": "● Honda SENSING",
  "● L2": "● レベル2",
  "● 百度": "● Baidu",
  "● 高速路段": "● 高速道路区間",
  "● 铝合金": "● アルミ合金",
  "● 遥控钥匙": "● リモコンキー",
  "● 遥控钥匙 蓝牙钥匙": "● リモコンキー＋Bluetoothキー",
  "● 前排": "● 前席",
  "● LED": "● LED",
  "● 可开启全景天窗": "● 開閉式パノラマサンルーフ",
  "● 驾驶位": "● 運転席",
  "● 主驾驶+照明灯 副驾驶+照明灯": "● 運転席＋照明灯 助手席＋照明灯",
  "● 雨量感应式": "● 雨量感知式",
  "● 电动调节 电动折叠 锁车自动折叠": "● 電動調整 電動格納 鍵施錠時自動格納",
  "● 电动调节 电动折叠 后视镜加热 倒车自动下翻 锁车自动折叠": "● 電動調整 電動格納 ミラー加熱 バック時自動下向き 鍵施錠時自動格納",
  "● 电动调节 电动折叠 后视镜记忆 后视镜加热 倒车自动下翻 锁车自动折叠": "● 電動調整 電動格納 ミラーメモリー ミラー加熱 バック時自動下向き 鍵施錠時自動格納",
  "● 触控液晶屏": "● タッチ液晶ディスプレイ",
  "● 12.3英寸": "● 12.3インチ",
  "● 10.1英寸": "● 10.1インチ",
  "● 支持CarPlay 支持CarLife 支持HUAWEI HiCar": "● CarPlay対応 CarLife対応 HUAWEI HiCar対応",
  "● 支持CarLife": "● CarLife対応",
  "● 多媒体系统 导航 电话 空调 车窗": "● マルチメディアシステム（ナビ・電話・エアコン・パワーウインドウ）",
  "● 你好，本田": "● こんにちは、ホンダ",
  "● 单区域": "● シングルゾーン",
  "● Honda Connect": "● Honda Connect",
  "● 4G": "● 4G",
  "● 车门控制 空调控制 车况查询/诊断 车辆定位/寻车": "● ドア操作 エアコン操作 車両状態確認・診断 車両位置特定・車両探索",
  "● 车门控制 车辆启动 空调控制 车况查询/诊断 车辆定位/寻车": "● ドア操作 エンジン始動 エアコン操作 車両状態確認・診断 車両位置特定・車両探索",
  "● 车门控制 车辆启动 车灯控制 空调控制 车况查询/诊断 车辆定位/寻车": "● ドア操作 エンジン始動 ライト操作 エアコン操作 車両状態確認・診断 車両位置特定・車両探索",
  "● 车门控制 车窗控制 车辆启动 车灯控制 空调控制 车况查询/诊断 车辆定位/寻车": "● ドア操作 パワーウインドウ操作 エンジン始動 ライト操作 エアコン操作 車両状態確認・診断 車両位置特定・車両探索",
  "● 车门控制 车辆启动 车况查询/诊断 车辆定位/寻车": "● ドア操作 エンジン始動 車両状態確認・診断 車両位置特定・車両探索",
  "● 塑料": "● プラスチック",
  "● 真皮": "● 本革",
  "● 手动上下+前后调节": "● 手動上下＋前後調整",
  "● 按键式换挡": "● ボタン式シフト",
  "● 机械挡把换挡": "● メカニカルシフトレバー",
  "● 彩色": "● カラー",
  "● 10.2英寸": "● 10.2インチ",
  "● 7英寸": "● 7インチ",
  "● 手动防眩目": "● 手動防眩目",
  "● 自动防眩目": "● 自動防眩目",
  "● 自动防眩目 流媒体": "● 自動防眩目＋デジタルインナーミラー",
  "● Type-C": "● Type-C",
  "● USB Type-C": "● USB Type-C",
  "● 前排2个/后排2个": "● 前席2個／後席2個",
  "● 50W": "● 50W",
  "● 织物": "● ファブリック",
  "● 前后调节 靠背调节 高低调节(2向)": "● 前後調整 背もたれ調整 高さ調整（2方向）",
  "● 前后调节 靠背调节 高低调节(4向) 腰部支撑(4向)": "● 前後調整 背もたれ調整 高さ調整（4方向） 腰部サポート（4方向）",
  "● 前后调节 靠背调节": "● 前後調整 リクライニング調整",
  "● 加热 通风": "● 加熱 通風",
  "● 加热": "● 加熱",
  "● 2-3-2": "● 2-3-2",
  "● 比例放倒": "● 分割可倒",
  "● BOSE": "● BOSE",
  "● 4喇叭": "● 4スピーカー",
  "● 8喇叭": "● 8スピーカー",
  "● 12喇叭": "● 12スピーカー",
  "● 多色": "● 多色",
  "● 单色": "● 単色",
  "● 自动空调": "● オートエアコン",
  "彩晶黑 皓月白 摩登灰 烟雨青": "彩晶ブラック 皓月ホワイト モダングレー 煙雨ブルー",
  "彩晶黑 晶耀白 摩登灰": "彩晶ブラック 晶耀ホワイト モダングレー",
  "彩晶黑 雅韵金 皓月白 赤焰红 星辰蓝": "彩晶ブラック 雅韻ゴールド 皓月ホワイト 赤焔レッド 星辰ブルー",
  "彩晶黑 赤霞红 雅韵金 晶耀白 星辰蓝": "彩晶ブラック 赤霞レッド 雅韻ゴールド 晶耀ホワイト 星辰ブルー",
  "黑色 黑色/棕色": "ブラック ブラック/ブラウン",
  "黑色 黑色/灰色": "ブラック ブラック/グレー",
  "黑色": "ブラック",
  "黑色/棕色": "ブラック/ブラウン"
}